cnv_from_bam-0.4.3.dist-info/METADATA
cnv_from_bam-0.4.3.dist-info/WHEEL
cnv_from_bam-0.4.3.dist-info/license_files/LICENSE
cnv_from_bam/__init__.py
cnv_from_bam/cnv_from_bam.pypy39-pp73-aarch64-linux-gnu.so
cnv_from_bam-0.4.3.dist-info/RECORD
