Metadata-Version: 2.1
Name: cnv_from_bam
Version: 0.4.3
Classifier: Programming Language :: Rust
Classifier: Programming Language :: Python :: Implementation :: CPython
Classifier: Topic :: Scientific/Engineering :: Bio-Informatics
Classifier: Programming Language :: Python :: Implementation :: PyPy
Classifier: Intended Audience :: Science/Research
Requires-Dist: pytest ; extra == 'dev'
Requires-Dist: pre-commit ; extra == 'dev'
Requires-Dist: pytest-benchmark[histogram] ; extra == 'dev'
Provides-Extra: dev
License-File: LICENSE
Author-email: Adoni5 <roryjmunro1@gmail.com>
License: MPL2
Requires-Python: >=3.8
Project-URL: Documentation, https://github.com/adoni5/cnv_from_bam#readme
Project-URL: Issues, https://github.com/adoni5/cnv_from_bam/issues
Project-URL: Source, https://github.com/adoni5/cnv_from_bam
